[
  {
    "type": "file",
    "name": "overview",
    "label": "健康检查概述"
  },
  {
    "type": "file",
    "name": "liveness",
    "label": "存活探针（Liveness Probe）"
  },
  {
    "type": "file",
    "name": "readiness",
    "label": "就绪探针（Readiness Probe）"
  },
  {
    "type": "file",
    "name": "startup",
    "label": "启动探针（Startup Probe）"
  },
  {
    "type": "file",
    "name": "probe-best-practices",
    "label": "探针实现最佳实践"
  },
  {
    "type": "file",
    "name": "endpoint-design",
    "label": "健康检查端点设计"
  },
  {
    "type": "file",
    "name": "spring-actuator",
    "label": "Spring Boot Actuator 健康检查"
  },
  {
    "type": "file",
    "name": "k8s-probes",
    "label": "Kubernetes 探针配置"
  },
  {
    "type": "file",
    "name": "graceful-shutdown",
    "label": "优雅关闭（Graceful Shutdown）"
  },
  {
    "type": "file",
    "name": "graceful-shutdown-implementation",
    "label": "优雅关闭实现方案"
  },
  {
    "type": "file",
    "name": "warm-up",
    "label": "流量预热与冷启动"
  },
  {
    "type": "file",
    "name": "self-healing",
    "label": "自愈机制设计"
  },
  {
    "type": "file",
    "name": "auto-restart",
    "label": "自动重启与重调度"
  }
]
