[
  { "type": "file", "name": "overview", "label": "Kubernetes 概述与架构" },
  { "type": "file", "name": "control-plane", "label": "控制平面组件" },
  { "type": "file", "name": "node-components", "label": "工作节点组件" },
  { "type": "divider" },
  { "type": "file", "name": "pod", "label": "Pod 深度解析" },
  { "type": "file", "name": "pod-lifecycle", "label": "Pod 生命周期与钩子" },
  { "type": "file", "name": "service", "label": "Service 详解" },
  { "type": "file", "name": "ingress", "label": "Ingress 与 Ingress Controller" },
  { "type": "file", "name": "configmap-secret", "label": "ConfigMap 与 Secret" },
  { "type": "file", "name": "volume", "label": "Volume 与 PVC/PV" },
  { "type": "file", "name": "storageclass", "label": "StorageClass 动态存储" },
  { "type": "divider" },
  { "type": "file", "name": "deployment", "label": "Deployment 与 ReplicaSet" },
  { "type": "file", "name": "statefulset", "label": "StatefulSet 有状态应用" },
  { "type": "file", "name": "daemonset", "label": "DaemonSet 守护进程" },
  { "type": "file", "name": "job", "label": "Job 与 CronJob" },
  { "type": "divider" },
  { "type": "file", "name": "hpa", "label": "HPA（水平自动伸缩）" },
  { "type": "file", "name": "vpa", "label": "VPA（垂直自动伸缩）" },
  { "type": "divider" },
  { "type": "file", "name": "crd", "label": "CRD（自定义资源定义）" },
  { "type": "file", "name": "operator", "label": "Operator 模式深度解析" },
  { "type": "file", "name": "operator-development", "label": "Operator 开发实战" },
  { "type": "divider" },
  { "type": "file", "name": "network-model", "label": "Kubernetes 网络模型" },
  { "type": "file", "name": "cni", "label": "CNI 插件对比" },
  { "type": "file", "name": "network-policy", "label": "NetworkPolicy 网络策略" },
  { "type": "divider" },
  { "type": "file", "name": "scheduler", "label": "Kubernetes 调度器原理" },
  { "type": "file", "name": "affinity", "label": "调度策略与亲和性" },
  { "type": "file", "name": "taint-toleration", "label": "污点与容忍" },
  { "type": "divider" },
  { "type": "file", "name": "security", "label": "Kubernetes 安全" },
  { "type": "file", "name": "pod-security", "label": "Pod 安全策略" },
  { "type": "divider" },
  { "type": "file", "name": "monitoring", "label": "Kubernetes 监控" },
  { "type": "file", "name": "logging", "label": "Kubernetes 日志收集" },
  { "type": "file", "name": "troubleshooting", "label": "Kubernetes 故障排查" },
  { "type": "file", "name": "upgrade", "label": "K8s 升级与版本管理" },
  { "type": "divider" },
  { "type": "file", "name": "multi-cluster", "label": "多集群管理" }
]
