[
  { "type": "file", "name": "overview", "label": "分片策略总览" },
  { "type": "file", "name": "range", "label": "范围分片（Range Sharding）" },
  { "type": "file", "name": "hash", "label": "哈希分片（Hash Sharding）" },
  { "type": "file", "name": "consistent-hashing", "label": "一致性哈希原理与实现" },
  { "type": "file", "name": "virtual-nodes", "label": "虚拟节点与负载均衡" },
  { "type": "file", "name": "directory", "label": "目录分片（Directory-Based Sharding）" },
  { "type": "file", "name": "geo", "label": "地理分片（Geographic Sharding）" },
  { "type": "file", "name": "hotspot", "label": "热点数据处理策略" },
  { "type": "file", "name": "shard-key", "label": "分片键设计最佳实践" },
  { "type": "file", "name": "rebalancing", "label": "动态分片与重平衡" },
  { "type": "file", "name": "query-challenges", "label": "分片带来的查询挑战" },
  { "type": "file", "name": "secondary-index", "label": "分片与二级索引" },
  { "type": "file", "name": "sharding-vs-partitioning", "label": "分片 vs 分区（Partitioning vs Sharding）" }
]
